uipathlib/__init__.py
uipathlib/__main__.py
uipathlib/models.py
uipathlib/uipath.py
uipathlib-0.0.12.dist-info/licenses/LICENSE
uipathlib-0.0.12.dist-info/METADATA
uipathlib-0.0.12.dist-info/WHEEL
uipathlib-0.0.12.dist-info/top_level.txt
uipathlib-0.0.12.dist-info/RECORD
